docker_credential_aws_sm/__init__.py
docker_credential_aws_sm/credentials.py
docker_credential_aws_sm-0.1.dist-info/LICENSE
docker_credential_aws_sm-0.1.dist-info/METADATA
docker_credential_aws_sm-0.1.dist-info/WHEEL
docker_credential_aws_sm-0.1.dist-info/entry_points.txt
docker_credential_aws_sm-0.1.dist-info/top_level.txt
docker_credential_aws_sm-0.1.dist-info/RECORD
