Metadata-Version: 2.1
Name: docker-credential-aws-sm
Version: 0.1
Summary: Allows storing Docker registry credentials using AWS SecretsManager
Home-page: https://github.com/szczad/docker-credential-aws-sm
Author: Grzegorz Szczudlik
Author-email: UNKNOWN
License: MIT
Keywords: docker,credentials,aws,secretsmanager
Platform: UNKNOWN
Requires-Dist: boto3
